llm4shell/__init__.py
llm4shell/llm.py
llm4shell/utils.py
llm4shell-0.4.1.dist-info/METADATA
llm4shell-0.4.1.dist-info/WHEEL
llm4shell-0.4.1.dist-info/entry_points.txt
llm4shell-0.4.1.dist-info/top_level.txt
llm4shell-0.4.1.dist-info/RECORD
