Metadata-Version: 2.1
Name: llm4shell
Version: 0.4.1
Summary: My LLM tools for shell tasks
Requires-Python: >=3.10
Requires-Dist: click>=8.0.0
Requires-Dist: colored>=2.2.4
Requires-Dist: litellm>=1.53.5
Requires-Dist: loguru>=0.7.2
Requires-Dist: parse>=1.20.2
